[
    {"name": "Aeulestraße"},
    {"name": "Ahornweg"},
    {"name": "Aischbachstraße"},
    {"name": "Aixer Straße"},
    {"name": "Albrechtstraße"},
    {"name": "Alexanderstraße"},
    {"name": "Alter Güterbahnhof"},
    {"name": "Am Mühlbach"},
    {"name": "Ammergasse"},
    {"name": "Amselweg"},
    {"name": "Auf dem Kreuz"},
    {"name": "Auf der Morgenstelle"},
    {"name": "August-Bebel-Straße"},
    {"name": "B.-v.Stuttner-Straße"},
    {"name": "BG Unfallklinik"},
    {"name": "Beethovenweg"},
    {"name": "Bei den Römergräbern"},
    {"name": "Bei der Kirche"},
    {"name": "Benzstraße"},
    {"name": "Bergfriedhof Ost"},
    {"name": "Bergfriedhof Süd"},
    {"name": "Bergfriedhof West"},
    {"name": "Betriebshof TüBus"},
    {"name": "Biererstraße"},
    {"name": "Biesingerstraße"},
    {"name": "Bismarckstraße"},
    {"name": "Bismarckturm"},
    {"name": "Bläsibad"},
    {"name": "Blaue Brücke"},
    {"name": "Botanischer Garten"},
    {"name": "Breiter Weg"},
    {"name": "Brückenstraße"},
    {"name": "Brühlstraße"},
    {"name": "Brunsstraße"},
    {"name": "Bühl Rathaus"},
    {"name": "Bühl Römerstraße"},
    {"name": "Bürgeramt"},
    {"name": "Burgholzweg"},
    {"name": "Calwerstraße"},
    {"name": "Carlo-Steeb-Str."},
    {"name": "Corrensstraße"},
    {"name": "Danziger Straße"},
    {"name": "Deichelweg"},
    {"name": "Derendingen Bahnhof"},
    {"name": "Dieselstraße"},
    {"name": "Doblerstraße"},
    {"name": "Dorfackerschule"},
    {"name": "Dorfstraße"},
    {"name": "Düsseldorfer Straße"},
    {"name": "Egeriaplatz"},
    {"name": "Eichhaldenstraße"},
    {"name": "Engelfriedshalde"},
    {"name": "Erlenweg"},
    {"name": "Ernst-Bloch-Straße"},
    {"name": "Ernst-Simon-Straße"},
    {"name": "Ersatzhaltestelle Aixer Straße"},
    {"name": "Ersatzhaltestelle Hagelloch Rathaus"},
    {"name": "Falkenweg"},
    {"name": "Ferd.-Chr.-Baur-Str."},
    {"name": "Feuerhägle Berufliche Schulen"},
    {"name": "Feuerhägle"},
    {"name": "Feuerhägle Städt. Schulen"},
    {"name": "Fichtenweg"},
    {"name": "Finanzamt"},
    {"name": "Franz. Viertel"},
    {"name": "Freibad"},
    {"name": "Fried.-Zundel-Str."},
    {"name": "Friedrich-Dannenmann-Straße"},
    {"name": "Fritz-Bauer-Straße"},
    {"name": "Frondsbergstraße"},
    {"name": "Fuchsstraße"},
    {"name": "Galgenberg"},
    {"name": "Gartenstraße"},
    {"name": "Gerstenmühlstraße"},
    {"name": "Gmelinstraße"},
    {"name": "Görlitzer Weg"},
    {"name": "Gösstraße"},
    {"name": "Goethestraße"},
    {"name": "Gottfr.-Pressel-Weg"},
    {"name": "Gottlieb-Olpp-Straße"},
    {"name": "Gottlob-Braeuning-Straße"},
    {"name": "Haagtor"},
    {"name": "Hagelloch Dornäckerweg"},
    {"name": "Hagelloch Rathaus"},
    {"name": "Hagellocher Weg"},
    {"name": "Hans-Geiger-Weg"},
    {"name": "Hasenbühl"},
    {"name": "Hauptbahnhof"},
    {"name": "Hauptbahnhof Süd"},
    {"name": "Haußerstraße"},
    {"name": "Haydnweg"},
    {"name": "Hechinger Eck"},
    {"name": "Hechinger Straße"},
    {"name": "Hegelstraße"},
    {"name": "Heinlenstraße"},
    {"name": "Hennentalweg"},
    {"name": "Hermann-Hepper-Halle"},
    {"name": "Herrenberger Straße"},
    {"name": "Herrlesberg"},
    {"name": "Hirschau Kirchplatz"},
    {"name": "Hirschau Volksbank"},
    {"name": "Hirschauer Straße"},
    {"name": "Hölderlinstraße"},
    {"name": "Horemer"},
    {"name": "Hornstraße"},
    {"name": "Hügelschule"},
    {"name": "Hundskapfklinge"},
    {"name": "Im Hopfengarten"},
    {"name": "Im Rotbad"},
    {"name": "Im Winkelrain"},
    {"name": "Jürgensenstraße ERSATZ"},
    {"name": "Jürgensenstraße"},
    {"name": "Jugendherberge"},
    {"name": "Käppele"},
    {"name": "Käthe-Kollwitz-Str."},
    {"name": "Kelternplatz"},
    {"name": "Kielmeyerstraße"},
    {"name": "Kiesäckerstraße"},
    {"name": "Kilchberg Bahnhof"},
    {"name": "Kilchberg Ehingenstraße"},
    {"name": "Kilchberg Keltengrab"},
    {"name": "Kilchberg Rathaus"},
    {"name": "Kilchberg Schloß"},
    {"name": "Kilchberg Schloß L370"},
    {"name": "Kleiststraße"},
    {"name": "Königsberger Straße"},
    {"name": "Kreßbach Kleeacker"},
    {"name": "Kreßbach Schloss"},
    {"name": "Kreuzberg"},
    {"name": "Kreuzstraße"},
    {"name": "Krumme Brücke"},
    {"name": "Kunsthalle"},
    {"name": "Landestheater"},
    {"name": "Landhausstraße"},
    {"name": "Lichtenberger Weg"},
    {"name": "Linsenbergstraße"},
    {"name": "Loretto"},
    {"name": "Lothar-Meyer-Bau"},
    {"name": "Lustnau Bahnhof"},
    {"name": "Maienfeldstraße"},
    {"name": "Maria-von-Linden-Straße"},
    {"name": "Marienstraße"},
    {"name": "Max-Planck-Institute"},
    {"name": "Memmingerstraße"},
    {"name": "Mohlstraße"},
    {"name": "Moltkestraße"},
    {"name": "Mühlbachäcker"},
    {"name": "Mühlenviertel"},
    {"name": "Mühlstraße"},
    {"name": "Neckarbrücke"},
    {"name": "Neckarhalde"},
    {"name": "Neckarsulmer Straße"},
    {"name": "Nelkenweg"},
    {"name": "Neuffenstraße"},
    {"name": "Neuhalde"},
    {"name": "Neuhaldenstraße ERSATZ"},
    {"name": "Neuhaldenstraße"},
    {"name": "Niethammerstraße"},
    {"name": "Nonnenhaus"},
    {"name": "Nürtinger Straße"},
    {"name": "Öhlerweg"},
    {"name": "Österberg"},
    {"name": "Österbergstraße"},
    {"name": "Oberndorf Feuersee"},
    {"name": "Oberndorf Rottenburger Str."},
    {"name": "Ochsenweide"},
    {"name": "Pappelweg"},
    {"name": "Parkhaus König"},
    {"name": "Paul-Dietz-Straße"},
    {"name": "Pauline-Krone-Heim"},
    {"name": "Pfrondorf Hermann-Reuchlin-Straße"},
    {"name": "Pfrondorf Lindenstraße"},
    {"name": "Pfrondorf Lusstraße"},
    {"name": "Pfrondorf Rathaus"},
    {"name": "Pfrondorf Schönbuchhalle"},
    {"name": "Pfrondorf Seestraße"},
    {"name": "Pfrondorf Steinbruchstraße"},
    {"name": "Pfrondorf Zollernstraße"},
    {"name": "Poltringen Ammerbrücke"},
    {"name": "Poststraße"},
    {"name": "Quenstedtstraße"},
    {"name": "Rappenberg"},
    {"name": "Rappstraße"},
    {"name": "Rechter Österberg"},
    {"name": "Regierungspräsidium"},
    {"name": "Rheinlandstraße"},
    {"name": "Rittweg Ost"},
    {"name": "Rittweg West"},
    {"name": "Robert-Gradmann-Weg"},
    {"name": "Rottenburg E.-Bolz-Platz"},
    {"name": "Rottenburg Friedhof Sülchen"},
    {"name": "Rottenburg Sülchenstraße"},
    {"name": "Rümelinstraße"},
    {"name": "Sand Drosselweg"},
    {"name": "Sand Nordring"},
    {"name": "Schaffhausenstraße"},
    {"name": "Schleifmühleweg"},
    {"name": "Schönblick"},
    {"name": "Schwabstraße"},
    {"name": "Schwärzl. Straße 111"},
    {"name": "Schwärzl. Straße 45"},
    {"name": "Schwärzl. Straße 79"},
    {"name": "Schwärzlocher Täle"},
    {"name": "Schweickhardtstraße"},
    {"name": "Sindelfinger Straße (B296)"},
    {"name": "Sindelfinger Straße"},
    {"name": "Sophienpflege"},
    {"name": "Sperberweg"},
    {"name": "Stadtgraben"},
    {"name": "Stadtwerke"},
    {"name": "Städtischer Fuhrpark"},
    {"name": "Stäudach"},
    {"name": "Stauden"},
    {"name": "Stauffenbergstraße"},
    {"name": "Steige"},
    {"name": "Stephanuskirche"},
    {"name": "Sternplatz"},
    {"name": "Sternwarte"},
    {"name": "Straßburger Äcker"},
    {"name": "Stuttgarter Straße"},
    {"name": "Sudetenstraße"},
    {"name": "Tilsiter Weg"},
    {"name": "Tropenklinik"},
    {"name": "Ulmenweg"},
    {"name": "Uni / Neue Aula"},
    {"name": "Uni-Kliniken Berg"},
    {"name": "Uni-Kliniken Tal"},
    {"name": "Untere Heulandsteige"},
    {"name": "Unteres Burgholz"},
    {"name": "Unterjesingen Kreissparkasse"},
    {"name": "Unterjesingen Mitte"},
    {"name": "Unterjesingen Sandäcker"},
    {"name": "Unterjesingen Süd"},
    {"name": "Ursrainer Ring"},
    {"name": "Viktor-Renner-Straße"},
    {"name": "Vor dem Kreuzberg"},
    {"name": "Waldhäuser Straße"},
    {"name": "Waldhörnle"},
    {"name": "Waldhörnlestraße"},
    {"name": "Wankheimer Täle"},
    {"name": "Wanne Kunsthalle"},
    {"name": "Weberstraße"},
    {"name": "Weilerhalde"},
    {"name": "Weilheim Alte Landstraße"},
    {"name": "Weilheim Kneiple"},
    {"name": "Weilheim Rathaus"},
    {"name": "Weißdornweg"},
    {"name": "Wendelsheim Adlerplatz"},
    {"name": "Wendelsheim Schwabstraße"},
    {"name": "Wennfelder Garten"},
    {"name": "Westbahnhof"},
    {"name": "Weststadt"},
    {"name": "Wielandshöhe"},
    {"name": "Wilhelmstraße"},
    {"name": "Windfeldstraße"},
    {"name": "Winkelwiese"},
    {"name": "Wolfgang-Stock-Str."},
    {"name": "Wolfsbaumweg"},
    {"name": "Wurmlingen Lindenstr."},
    {"name": "Wurmlingen Rössle"}
]
